sixfinger/__init__.py
sixfinger/api.py
sixfinger/errors.py
sixfinger/models.py
sixfinger/transformers/__init__.py
sixfinger/transformers/cli/__init__.py
sixfinger/transformers/cli/generate.py
sixfinger/transformers/cli/train.py
sixfinger/transformers/generation/__init__.py
sixfinger/transformers/generation/sampling.py
sixfinger/transformers/models/__init__.py
sixfinger/transformers/models/speedlm.py
sixfinger/transformers/utils/__init__.py
sixfinger/transformers/utils/checkpoint.py
sixfinger/transformers/utils/logger.py
sixfinger-2.1.0.dist-info/licenses/LICENSE
sixfinger-2.1.0.dist-info/METADATA
sixfinger-2.1.0.dist-info/WHEEL
sixfinger-2.1.0.dist-info/entry_points.txt
sixfinger-2.1.0.dist-info/top_level.txt
sixfinger-2.1.0.dist-info/RECORD
