Metadata-Version: 2.4
Name: sixfinger
Version: 2.1.0
Summary: Ultra-fast AI platform: Cloud API + On-device language models
Home-page: https://sfapi.pythonanywhere.com
Author: Sixfinger Team
Author-email: Sixfinger Team <sixfingerdev@gmail.com>
License: MIT
Project-URL: Homepage, https://sfapi.pythonanywhere.com
Project-URL: Documentation, https://sfapi.pythonanywhere.com/docs
Project-URL: Repository, https://github.com/sixfinger/sixfinger-python
Project-URL: Changelog, https://github.com/sixfinger/sixfinger-python/blob/main/CHANGELOG.md
Keywords: ai,chatbot,api,llm,sixfinger,artificial-intelligence,transformers,on-device,cpu-optimized,mobile-ml
Classifier: Development Status :: 5 - Production/Stable
Classifier: Intended Audience :: Developers
Classifier: Topic :: Software Development :: Libraries :: Python Modules
Classifier: Topic :: Scientific/Engineering :: Artificial Intelligence
Classifier: License :: OSI Approved :: MIT License
Classifier: Programming Language :: Python :: 3
Classifier: Programming Language :: Python :: 3.7
Classifier: Programming Language :: Python :: 3.8
Classifier: Programming Language :: Python :: 3.9
Classifier: Programming Language :: Python :: 3.10
Classifier: Programming Language :: Python :: 3.11
Classifier: Programming Language :: Python :: 3.12
Requires-Python: >=3.7
License-File: LICENSE
Requires-Dist: requests>=2.25.0
Provides-Extra: async
Requires-Dist: aiohttp>=3.8.0; extra == "async"
Provides-Extra: transformers
Requires-Dist: numpy>=1.19.0; extra == "transformers"
Requires-Dist: tqdm>=4.50.0; extra == "transformers"
Provides-Extra: transformers-fast
Requires-Dist: numpy>=1.19.0; extra == "transformers-fast"
Requires-Dist: tqdm>=4.50.0; extra == "transformers-fast"
Requires-Dist: numba>=0.53.0; extra == "transformers-fast"
Provides-Extra: all
Requires-Dist: aiohttp>=3.8.0; extra == "all"
Requires-Dist: numpy>=1.19.0; extra == "all"
Requires-Dist: tqdm>=4.50.0; extra == "all"
Provides-Extra: dev
Requires-Dist: pytest>=6.0; extra == "dev"
Requires-Dist: pytest-cov>=2.12; extra == "dev"
Requires-Dist: black>=21.0; extra == "dev"
Requires-Dist: flake8>=3.9; extra == "dev"
Requires-Dist: mypy>=0.900; extra == "dev"
Dynamic: author
Dynamic: home-page
Dynamic: license-file
Dynamic: requires-python
